{
	"Id": "loot_mix_food_med_ammo (245)4933612",
	"IsStatic": false,
	"useGravity": true,
	"randomRotation": true,
	"Position": {
		"x": 243.456421,
		"y": 20.1748085,
		"z": 212.044678
	},
	"Rotation": {
		"x": 0,
		"y": 0,
		"z": 0
	},
	"IsGroupPosition": false,
	"GroupPositions": [],
	"Root": "5d31e403645bb7383252fcb6",
	"Items": [
		{
			"_id": "5d31e403645bb7383252fcb6",
			"_tpl": "57372fc52459776998772ca1"
		},
		{
			"_id": "5d31e403645bb7383252fcb7",
			"_tpl": "56dff4ecd2720b5f5a8b4568",
			"parentId": "5d31e403645bb7383252fcb6",
			"slotId": "cartridges",
			"upd": {
				"StackObjectsCount": 60
			}
		},
		{
			"_id": "5d31e403645bb7383252fcb8",
			"_tpl": "56dff4ecd2720b5f5a8b4568",
			"parentId": "5d31e403645bb7383252fcb6",
			"slotId": "cartridges",
			"location": 1,
			"upd": {
				"StackObjectsCount": 60
			}
		}
	]
}