{
	"Id": "quest_case2035535982",
	"IsStatic": false,
	"useGravity": false,
	"randomRotation": false,
	"Position": {
		"x": 178.07,
		"y": 2.877,
		"z": 148.702
	},
	"Rotation": {
		"x": 0.00000170754754,
		"y": 0,
		"z": 0
	},
	"IsGroupPosition": false,
	"GroupPositions": [],
	"Root": "5db5d0438bcb9e33ce400836",
	"Items": [
		{
			"_id": "5db5d0438bcb9e33ce400836",
			"_tpl": "590dde5786f77405e71908b2"
		},
		{
			"_id": "5db5d0438bcb9e33ce400837",
			"_tpl": "5449016a4bdc2d6f028b456f",
			"parentId": "5db5d0438bcb9e33ce400836",
			"slotId": "main",
			"location": {
				"x": 0,
				"y": 0,
				"r": 0
			},
			"upd": {
				"StackObjectsCount": 606
			}
		}
	]
}