{
	"Id": "Lootable_00167",
	"IsStatic": true,
	"useGravity": true,
	"randomRotation": false,
	"Position": {
		"x": 0,
		"y": 0,
		"z": 0
	},
	"Rotation": {
		"x": 0,
		"y": 0,
		"z": 0
	},
	"IsGroupPosition": false,
	"GroupPositions": [],
	"Root": "5dd2955d86f774793e1ed72d",
	"Items": [
		{
			"_id": "5dd2955d86f774793e1ed72d",
			"_tpl": "5909d5ef86f77467974efbd8"
		},
		{
			"_id": "5dd2955d86f774793e1ed72e",
			"_tpl": "5926f34786f77469195bfe92",
			"parentId": "5dd2955d86f774793e1ed72d",
			"slotId": "main",
			"location": {
				"x": 0,
				"y": 0,
				"r": 0
			}
		}
	]
}