{
	"Id": "Lootable_00236",
	"IsStatic": true,
	"useGravity": true,
	"randomRotation": false,
	"Position": {
		"x": 0,
		"y": 0,
		"z": 0
	},
	"Rotation": {
		"x": 0,
		"y": 0,
		"z": 0
	},
	"IsGroupPosition": false,
	"GroupPositions": [],
	"Root": "5e0675d80b8cde1bad7223aa",
	"Items": [
		{
			"_id": "5e0675d80b8cde1bad7223aa",
			"_tpl": "5909d5ef86f77467974efbd8"
		},
		{
			"_id": "5e0675d80b8cde1bad7223ab",
			"_tpl": "5bed61680db834001d2c45ab",
			"parentId": "5e0675d80b8cde1bad7223aa",
			"slotId": "main",
			"location": {
				"x": 0,
				"y": 0,
				"r": 0
			}
		}
	]
}