{
	"Id": "loot_mix_food_med_ammo (25)5870832",
	"IsStatic": false,
	"useGravity": true,
	"randomRotation": true,
	"Position": {
		"x": -60.48059,
		"y": 22.6948128,
		"z": -280.0133
	},
	"Rotation": {
		"x": 0,
		"y": 143,
		"z": 0
	},
	"IsGroupPosition": false,
	"GroupPositions": [],
	"Root": "5e382a018e89a76b703a1043",
	"Items": [
		{
			"_id": "5e382a018e89a76b703a1043",
			"_tpl": "573727c624597765cc785b5b"
		},
		{
			"_id": "5e382a018e89a76b703a1044",
			"_tpl": "5737201124597760fc4431f1",
			"parentId": "5e382a018e89a76b703a1043",
			"slotId": "cartridges",
			"upd": {
				"StackObjectsCount": 16
			}
		}
	]
}