{
	"Id": "loot_mods (28)5862266",
	"IsStatic": false,
	"useGravity": true,
	"randomRotation": true,
	"Position": {
		"x": -16.371582,
		"y": 28.027813,
		"z": -16.3133545
	},
	"Rotation": {
		"x": 0,
		"y": 275,
		"z": 0
	},
	"IsGroupPosition": false,
	"GroupPositions": [],
	"Root": "5e382a1c7e788532af3601fe",
	"Items": [
		{
			"_id": "5e382a1c7e788532af3601fe",
			"_tpl": "571a29dc2459771fb2755a6a"
		},
		{
			"_id": "5e382a1c7e788532af3601ff",
			"_tpl": "573601b42459776410737435",
			"parentId": "5e382a1c7e788532af3601fe",
			"slotId": "cartridges",
			"upd": {
				"StackObjectsCount": 1
			}
		}
	]
}